BactInspector-0.0.4.dist-info/DESCRIPTION.rst
BactInspector-0.0.4.dist-info/METADATA
BactInspector-0.0.4.dist-info/RECORD
BactInspector-0.0.4.dist-info/WHEEL
BactInspector-0.0.4.dist-info/entry_points.txt
BactInspector-0.0.4.dist-info/metadata.json
BactInspector-0.0.4.dist-info/top_level.txt
bactinspector/__init__.py
bactinspector/mash_functions.py
bactinspector/run_bactinspector.py
bactinspector/utility_functions.py
bactinspector/data/refseq.genomes.k21s1000.species.tsv
